Metadata-Version: 2.1
Name: flac-numcodecs
Version: 0.1.2
Summary: Numcodecs implementation of FLAC audio codec.
Home-page: https://github.com/AllenNeuralDynamics/flac-numcodecs
Author: Alessio Buccino
Author-email: alessiop.buccino@gmail.com
License: UNKNOWN
Platform: UNKNOWN
Classifier: Programming Language :: Python :: 3
Classifier: License :: OSI Approved :: MIT License
Classifier: Operating System :: OS Independent
License-File: LICENSE
